MANIFEST.in
README.rst
requirements.txt
setup.py
package/__init__.py
package/rdspgbadger.py
package/which.py
rdspgbadger.egg-info/PKG-INFO
rdspgbadger.egg-info/SOURCES.txt
rdspgbadger.egg-info/dependency_links.txt
rdspgbadger.egg-info/entry_points.txt
rdspgbadger.egg-info/requires.txt
rdspgbadger.egg-info/top_level.txt
rdspgbadger.egg-info/zip-safe