Metadata-Version: 1.1
Name: rdspgbadger
Version: 1.2.2
Summary: Fetch logs from RDS postgres instance and use them with pgbadger to generate a report.
Home-page: http://github.com/fpietka/rds-pgbadger
Author: François Pietka
Author-email: francois@pietka.fr
License: MIT
Platform: UNKNOWN
Classifier: Intended Audience :: Developers
Classifier: License :: OSI Approved :: MIT License
Classifier: Environment :: Console
Classifier: Programming Language :: Python
Classifier: Programming Language :: Python :: 2.6
Classifier: Programming Language :: Python :: 2.7
Classifier: Programming Language :: Python :: 3
Classifier: Programming Language :: Python :: 3.3
Classifier: Programming Language :: Python :: 3.4
Classifier: Programming Language :: Python :: 3.5
Classifier: Programming Language :: Python :: 3.6
